LICENSE
README.md
setup.py
libpythonpro/__init__.py
libpythonpro/github_api.py
libpythonpromu.egg-info/PKG-INFO
libpythonpromu.egg-info/SOURCES.txt
libpythonpromu.egg-info/dependency_links.txt
libpythonpromu.egg-info/not-zip-safe
libpythonpromu.egg-info/requires.txt
libpythonpromu.egg-info/top_level.txt